inquire.py
setup.py
inquire.egg-info/PKG-INFO
inquire.egg-info/SOURCES.txt
inquire.egg-info/dependency_links.txt
inquire.egg-info/top_level.txt