Metadata-Version: 1.0
Name: inquire
Version: 0.12
Summary: Simplified collection and object querying for Python.
Home-page: UNKNOWN
Author: Tony Young
Author-email: rofflwaffls@gmail.com
License: UNKNOWN
Platform: UNKNOWN
